{"last_tab":"","logo-img":{"url":"https:\/\/essentials.pixfort.com\/construction\/wp-content\/uploads\/sites\/20\/2020\/06\/construction-logo.png","id":"5","height":"110","width":"560","thumbnail":"https:\/\/essentials.pixfort.com\/construction\/wp-content\/uploads\/sites\/20\/2020\/06\/construction-logo-150x110.png","title":"construction-logo","caption":"","alt":"","description":""},"retina-logo-img":{"url":"https:\/\/essentials.pixfort.com\/construction\/wp-content\/uploads\/sites\/20\/2020\/06\/construction-logo.png","id":"5","height":"110","width":"560","thumbnail":"https:\/\/essentials.pixfort.com\/construction\/wp-content\/uploads\/sites\/20\/2020\/06\/construction-logo-150x110.png","title":"construction-logo","caption":"","alt":"","description":""},"scroll-logo-img":{"url":"https:\/\/essentials.pixfort.com\/construction\/wp-content\/uploads\/sites\/20\/2020\/06\/construction-logo.png","id":"5","height":"110","width":"560","thumbnail":"https:\/\/essentials.pixfort.com\/construction\/wp-content\/uploads\/sites\/20\/2020\/06\/construction-logo-150x110.png","title":"construction-logo","caption":"","alt":"","description":""},"mobile-logo-img":{"url":"https:\/\/essentials.pixfort.com\/construction\/wp-content\/uploads\/sites\/20\/2020\/06\/construction-logo.png","id":"5","height":"110","width":"560","thumbnail":"https:\/\/essentials.pixfort.com\/construction\/wp-content\/uploads\/sites\/20\/2020\/06\/construction-logo-150x110.png","title":"construction-logo","caption":"","alt":"","description":""},"favicon-img":{"url":"https:\/\/essentials.pixfort.com\/construction\/wp-content\/uploads\/sites\/20\/2020\/06\/yellow-favicon.png","id":"74","height":"180","width":"180","thumbnail":"https:\/\/essentials.pixfort.com\/construction\/wp-content\/uploads\/sites\/20\/2020\/06\/yellow-favicon-150x150.png","title":"yellow-favicon","caption":"","alt":"","description":""},"pix-body-padding":"","pix-body-bg-color":"","custom-body-bg-color":"#FFFFFF","website-preview":{"url":"","id":"","height":"","width":"","thumbnail":"","title":"","caption":"","alt":"","description":""},"back-to-top":"default","pix-exit-popup":"","pix-exit-popup-id":"exit-popup-1","pix-automatic-popup":"","pix-automatic-popup-id":"automatic-popup-1","pix-automatic-popup-time":"5","pix_sidebars":[""],"google-api-key":"","pix-enable-cookies":"1","pix-cookies-id":"Cookies-1","pix-cookies-text":"By using this website, you agree to our","pix-cookies-btn":"cookie policy.","pix-cookies-page":"","pix-cookies-popup":"13336","pix-header":"13","pix-footer":"14","pix-sticky-footer":"1","sticky-footer-bg-color":"gradient-primary","custom-sticky-footer-bg-color":"#FFFFFF","show-banner":"","banner-id":"Banner-1","banner-text":"","banner-bg":"","custom-banner-bg":"#FFFFFF","banner-bg-img":{"url":"","id":"","height":"","width":"","thumbnail":"","title":"","caption":"","alt":"","description":""},"bold-banner-text":"1","secondary-banner-text":"","banner-text-color":"gray-9","banner-custom-text-color":"#212529","show-banner-btn":"","banner-btn-text":"Check it Now","banner-btn-link":"#","show-banner-target":"1","banner-btn-style":"","banner-btn-color":"primary","banner-btn-text-color":"","banner-btn-custom-text-color":"#212529","show-banner-countdown":"","banner-date":"2020-10-10T00:48","banner-padding":"","search-style":"4","opt-slider-label":"3","overlay-color-1-primary":"0","overlay-color-1":{"from":"#ffc845","to":"#ffc845"},"overlay-color-2":{"from":"#f48924","to":"#f48924"},"overlay-color-3":{"from":"#f85a40","to":"#f85a40"},"overlay-color-4":{"from":"#1e73be","to":"#00897e"},"social-skype":"","social-facebook":"https:\/\/www.facebook.com\/pixfort","social-google":"","social-twitter":"","social-vimeo":"","social-youtube":"https:\/\/www.youtube.com\/pixfort","social-flickr":"","social-linkedin":"https:\/\/www.linkedin.com\/pixfort","social-pinterest":"","social-dribbble":"","social-instagram":"https:\/\/www.instagram.com\/pixfort","social-snapchat":"","social-telegram":"","social-googleplay":"","social-appstore":"","social-whatsapp":"","opt-primary-color":"#ffc845","opt-secondary-color":"#f85a40","opt-link-color":"#333333","opt-primary-gradient-switch":"1","opt-color-gradient-primary-1":"#f85a40","opt-color-gradient-primary-middle":"#f48924","opt-color-gradient-primary-2":"#ffc845","opt-primary-gradient-dir":"to right","blog-posts":"8","blog-page-layout":"default","blog-grid-count":"4","blog-masonry-count":"3","blog-style":"right-img","blog-layout":"default","blog-style-box":"1","blog-bg-color":"gray-1","custom-blog-bg-color":"#FFFFFF","sidebar-blog":"sidebar-1","blog-box-rounded":"rounded-lg","blog-box-style":"1","blog-box-hover-effect":"1","blog-box-add-hover-effect":"1","post-with-intro":"1","blog-divider-style":"17","blog-divider-height":"","blog-intro-img":{"url":"https:\/\/essentials.pixfort.com\/construction\/wp-content\/uploads\/sites\/20\/2020\/06\/slider-image-2.jpg","id":"61","height":"700","width":"1600","thumbnail":"https:\/\/essentials.pixfort.com\/construction\/wp-content\/uploads\/sites\/20\/2020\/06\/slider-image-2-150x150.jpg","title":"slider-image-2","caption":"","alt":"","description":""},"blog-intro-light":"1","blog-intro-align":"text-center","blog-intr-bg-color":"gray-8","blog-intro-opacity":"pix-opacity-2","portfolio-posts":"8","portfolio-page-style":"default","portfolio-masonry-count":"4","portfolio-layout":"default","portfolio-order":"DESC","portfolio-navigation":"1","portfolio-in-same-term":"","portfolio-post-info":"","portfolio-related":"1","portfolio-isotope":"1","portfolio-slug":"portfolio-item","portfolio-bg-color":"gray-1","custom-portfolio-bg-color":"#FFFFFF","sidebar-portfolio":"sidebar-1","portfolio-orderby":"date","portfolio-with-intro":"1","portfolio-divider-style":"17","portfolio-divider-height":"","portfolio-intro-img":{"url":"https:\/\/essentials.pixfort.com\/construction\/wp-content\/uploads\/sites\/20\/2020\/06\/slider-image-3.jpg","id":"62","height":"700","width":"1600","thumbnail":"https:\/\/essentials.pixfort.com\/construction\/wp-content\/uploads\/sites\/20\/2020\/06\/slider-image-3-150x150.jpg","title":"slider-image-3","caption":"","alt":"","description":""},"portfolio-intro-light":"1","portfolio-intro-align":"text-center","portfolio-intr-bg-color":"gray-8","portfolio-intro-opacity":"pix-opacity-2","pages-bg-color":"gray-1","custom-pages-bg-color":"#FFFFFF","sidebar-page":"sidebar-1","pages-with-intro":"1","pages-divider-style":"17","pages-divider-height":"","pages-intro-img":{"url":"https:\/\/essentials.pixfort.com\/construction\/wp-content\/uploads\/sites\/20\/2020\/06\/slider-image-3.jpg","id":"62","height":"700","width":"1600","thumbnail":"https:\/\/essentials.pixfort.com\/construction\/wp-content\/uploads\/sites\/20\/2020\/06\/slider-image-3-150x150.jpg","title":"slider-image-3","caption":"","alt":"","description":""},"pages-intro-light":"1","pages-intro-align":"text-center","pages-intr-bg-color":"gray-8","pages-intro-opacity":"pix-opacity-2","opt-primary-font":{"font-family":"Manrope","font-options":"","google":"1","font-backup":"Arial, Helvetica, sans-serif"},"opt-primary-font-spacing":"-0.01rem","opt-secondary-font":{"font-family":"Manrope","font-options":"","google":"1","font-backup":"Arial, Helvetica, sans-serif"},"opt-secondary-font-spacing":"-0.03rem","opt-body-color":"gray-5","opt-custom-body-color":"#212529","opt-dark-body-color":"light-opacity-7","opt-custom-dark-body-color":"#eeeeee","opt-heading-color":"gray-7","opt-custom-heading-color":"#eeeeee","opt-dark-heading-color":"white","opt-custom-dark-heading-color":"#ffffff","opt-regular-font-weight":"","opt-bold-font-weight":"","opt-external-font-1-url":"","opt-external-font-1-name":"","opt-external-font-2-url":"","opt-external-font-2-name":"","shop-layout":"right-sidebar","shop-item-style":"default","shop-col-count":"3","shop-tabs-style":"pix-pills-1","shop-single-layout":"default","shop-single-sidebar":"","shop-bg-color":"gray-1","custom-shop-bg-color":"#FFFFFF","sidebar-shop":"sidebar-1","shop-with-intro":"1","shop-divider-style":"0","shop-divider-height":"","shop-intro-img":{"url":"https:\/\/essentials.pixfort.com\/construction\/wp-content\/uploads\/sites\/20\/2020\/06\/slider-image-2.jpg","id":"61","height":"700","width":"1600","thumbnail":"https:\/\/essentials.pixfort.com\/construction\/wp-content\/uploads\/sites\/20\/2020\/06\/slider-image-2-150x150.jpg","title":"slider-image-2","caption":"","alt":"","description":""},"shop-intro-light":"1","shop-intro-align":"text-center","shop-intr-bg-color":"gray-8","shop-intro-opacity":"pix-opacity-2","redux-backup":"1"}